slowroll/__init__.py
slowroll/api.py
slowroll/isoformat.py
slowroll/py.typed
slowroll/time_delta_str.py
slowroll/tests/__init__.py
slowroll/tests/__main__.py
slowroll/tests/api.py
slowroll/tests/time_delta_str.py
slowroll-0.0.1.dist-info/LICENSE
slowroll-0.0.1.dist-info/METADATA
slowroll-0.0.1.dist-info/WHEEL
slowroll-0.0.1.dist-info/top_level.txt
slowroll-0.0.1.dist-info/RECORD
