Metadata-Version: 2.1
Name: slowroll
Version: 0.0.1
Summary: Configuration slowly applied to clients over time
Home-page: https://github.com/python-packaging/slowroll
Author: Tim Hatch
Author-email: tim@timhatch.com
License: MIT
Requires-Python: >=3.8
License-File: LICENSE
Requires-Dist: deltaman
